xiek/__init__.py
xiek/httpclient/__init__.py
xiek/httpclient/base.py
xiek/httpclient/export.py
xiek/httpclient/request.py
xiek/httpclient/utils.py
xiek-1.0.0.dist-info/LICENSE
xiek-1.0.0.dist-info/METADATA
xiek-1.0.0.dist-info/WHEEL
xiek-1.0.0.dist-info/top_level.txt
xiek-1.0.0.dist-info/RECORD
